genomespaceclient/__init__.py
genomespaceclient/client.py
genomespaceclient/exceptions.py
genomespaceclient/gs_glob.py
genomespaceclient/shell.py
genomespaceclient/storage_handlers.py
genomespaceclient/util.py
python_genomespaceclient-1.1.0.dist-info/DESCRIPTION.rst
python_genomespaceclient-1.1.0.dist-info/METADATA
python_genomespaceclient-1.1.0.dist-info/RECORD
python_genomespaceclient-1.1.0.dist-info/WHEEL
python_genomespaceclient-1.1.0.dist-info/entry_points.txt
python_genomespaceclient-1.1.0.dist-info/metadata.json
python_genomespaceclient-1.1.0.dist-info/top_level.txt
test/__init__.py
test/helpers.py
test/test_genomespace_client.py
test/test_genomespace_shell.py
